dsrecords
