Metadata-Version: 2.1
Name: dsrecords
Version: 0.4.18
Summary: Dead-simple and easy-to-hack RecordIO-like data storing. Inspired by MXNet's RecordIO and Protobuf.
Author-email: Hung Nguyen <ndgnuh@protonmail.com>
License: MIT
Project-URL: Homepage, https://gitlab.com/ndgnuh/dsrecords
Project-URL: Documentation, https://ndgnuh.gitlab.io/dsrecords/
Project-URL: Bug tracker, https://gitlab.com/ndgnuh/dsrecords/-/issues
Keywords: RecordIO
Classifier: Programming Language :: Python :: 3
Classifier: License :: OSI Approved :: MIT License
Classifier: Operating System :: OS Independent
